hakcer/__init__.py
hakcer/banner.py
hakcer/themes.py
hakcer-1.2.4.dist-info/licenses/LICENSE
hakcer-1.2.4.dist-info/METADATA
hakcer-1.2.4.dist-info/WHEEL
hakcer-1.2.4.dist-info/entry_points.txt
hakcer-1.2.4.dist-info/top_level.txt
hakcer-1.2.4.dist-info/RECORD
