Metadata-Version: 2.4
Name: hakcer
Version: 1.2.4
Summary: Animated ASCII banner with terminal effects and customizable themes for CLI tools
Home-page: https://github.com/haKC-ai/hakcer
Author: haKCer
Author-email: haKCer <cory@haKC.ai>
Project-URL: Homepage, https://github.com/haKC-ai/hakcer
Project-URL: Bug Reports, https://github.com/haKC-ai/hakcer/issues
Project-URL: Source, https://github.com/haKC-ai/hakcer
Keywords: cli,banner,ascii,terminal,effects,animation,themes,tokyo-night,cyberpunk
Classifier: Development Status :: 4 - Beta
Classifier: Intended Audience :: Developers
Classifier: Topic :: Software Development :: Libraries :: Python Modules
Classifier: Topic :: Terminals
Classifier: Topic :: System :: Shells
Classifier: License :: OSI Approved :: MIT License
Classifier: Programming Language :: Python :: 3
Classifier: Programming Language :: Python :: 3.8
Classifier: Programming Language :: Python :: 3.9
Classifier: Programming Language :: Python :: 3.10
Classifier: Programming Language :: Python :: 3.11
Classifier: Programming Language :: Python :: 3.12
Classifier: Operating System :: OS Independent
Requires-Python: >=3.8
License-File: LICENSE
Requires-Dist: terminaltexteffects>=0.11.0
Requires-Dist: rich>=13.0.0
Provides-Extra: dev
Requires-Dist: pytest>=7.0.0; extra == "dev"
Requires-Dist: pytest-cov>=4.0.0; extra == "dev"
Requires-Dist: black>=23.0.0; extra == "dev"
Requires-Dist: flake8>=6.0.0; extra == "dev"
Dynamic: author
Dynamic: home-page
Dynamic: license-file
Dynamic: requires-python
